rdstest/__init__.py
rdstest/a.py
rdstest-0.0.2.dist-info/METADATA
rdstest-0.0.2.dist-info/WHEEL
rdstest-0.0.2.dist-info/top_level.txt
rdstest-0.0.2.dist-info/RECORD
