Metadata-Version: 2.1
Name: rdstest
Version: 0.0.2
Summary: test
Home-page: UNKNOWN
Author: Tanmay Varade
Author-email: <tanmayvarade235@gmail.com>
License: UNKNOWN
Keywords: python,compare,RDS,parameter,group,AWS,devops
Platform: UNKNOWN
Classifier: Programming Language :: Python :: 3
Classifier: License :: OSI Approved :: MIT License
Classifier: Operating System :: Unix
Classifier: Operating System :: MacOS :: MacOS X
Classifier: Operating System :: Microsoft :: Windows
Requires-Dist: pandas
